autopwn_suite/__init__.py
autopwn_suite/api.py
autopwn_suite/autopwn.py
autopwn_suite/modules/__init__.py
autopwn_suite/modules/banners.py
autopwn_suite/modules/getexploits.py
autopwn_suite/modules/logger.py
autopwn_suite/modules/nist_search.py
autopwn_suite/modules/random_user_agent.py
autopwn_suite/modules/report.py
autopwn_suite/modules/scanner.py
autopwn_suite/modules/searchvuln.py
autopwn_suite/modules/utils.py
autopwn_suite/modules/data/user_agents.json
autopwn_suite/modules/data/web_discovery.txt
autopwn_suite/modules/web/__init__.py
autopwn_suite/modules/web/crawler.py
autopwn_suite/modules/web/dirbust.py
autopwn_suite/modules/web/lfi.py
autopwn_suite/modules/web/sqli.py
autopwn_suite/modules/web/webvuln.py
autopwn_suite/modules/web/xss.py
autopwn_suite-2.1.2.dist-info/METADATA
autopwn_suite-2.1.2.dist-info/WHEEL
autopwn_suite-2.1.2.dist-info/entry_points.txt
autopwn_suite-2.1.2.dist-info/top_level.txt
autopwn_suite-2.1.2.dist-info/RECORD
