Metadata-Version: 2.1
Name: autopwn-suite
Version: 2.1.2
Summary: AutoPWN Suite is a project for scanning vulnerabilities and exploiting systems automatically.
Home-page: https://auto.pwnspot.com
Author: GamehunterKaan
License: EULA
Project-URL: Documentation, https://auto.pwnspot.com
Project-URL: Source, https://github.com/GamehunterKaan/AutoPWN-Suite
Project-URL: Tracker, https://github.com/GamehunterKaan/AutoPWN-Suite/issues
Platform: UNKNOWN
Classifier: Development Status :: 5 - Production/Stable
Classifier: Natural Language :: English
Classifier: Programming Language :: Python
Classifier: Environment :: Console
Classifier: Topic :: Security
Requires-Dist: bs4
Requires-Dist: distro
Requires-Dist: python-nmap
Requires-Dist: requests
Requires-Dist: rich
